fastqueue.py
_fastqueue.cpython-39-x86_64-linux-gnu.so
fastqueue_lib-0.0.17.dist-info/RECORD
fastqueue_lib-0.0.17.dist-info/top_level.txt
fastqueue_lib-0.0.17.dist-info/LICENSE
fastqueue_lib-0.0.17.dist-info/WHEEL
fastqueue_lib-0.0.17.dist-info/METADATA
fastqueue/ccqueue.so
fastqueue/prototypes.py
fastqueue/cllqueue.so
fastqueue/__init__.py
