Metadata-Version: 2.1
Name: fastqueue-lib
Version: 0.0.17
Summary: Fast single ended queue library for python
Author-email: Matthew Taylor <matthew.taylor.andre@gmail.com>
Project-URL: Homepage, https://github.com/MatthewAndreTaylor/fastqueue
Keywords: Queue
Classifier: Development Status :: 3 - Alpha
Classifier: Intended Audience :: Developers
Classifier: License :: OSI Approved :: MIT License
Classifier: Programming Language :: Python :: 3
Classifier: Programming Language :: Python :: 3 :: Only
Classifier: Programming Language :: Python :: 3.7
Classifier: Programming Language :: Python :: 3.8
Classifier: Programming Language :: Python :: 3.9
Classifier: Programming Language :: Python :: 3.10
Classifier: Programming Language :: Python :: 3.11
Classifier: Programming Language :: Python :: Implementation :: CPython
Classifier: Topic :: Software Development :: Libraries :: Python Modules
Requires-Python: >=3.7
License-File: LICENSE
Provides-Extra: examples
Requires-Dist: matplotlib ; extra == 'examples'
Requires-Dist: numpy ; extra == 'examples'
Requires-Dist: pandas ; extra == 'examples'
Provides-Extra: tests
Requires-Dist: pytest ; extra == 'tests'
